Lab 01/1.2.3/keypad.v
module keypad(valid, number, a, b, c, d, e, f, g);
   output   valid;
   output [3:0] number;
   input  a, b, c, d, e, f, g;

   wire na, nb, nc, nd, ne, nf, ng;

   not n1(na, a);
   not n2(nb, b);
   not n3(nc, c);
   not n4(nd, d);
   not n5(ne, e);
   not n6(nf, f);
   not n7(ng, g);

   // possible combinations:

   wire p0, p1, p2, p3, p4, p5, p6, p7, p8, p9;

   and a0(p0, na, b, nc, nd, ne, nf, g); // bg 0000
   and a1(p1, a, nb, nc, d, ne, nf, ng); // ad 0001
   and a2(p2, na, b, nc, d, ne, nf, ng); // bd 0010
   and a3(p3, na, nb, c, d, ne, nf, ng); // cd 0011
   and a4(p4, a, nb, nc, nd, e, nf, ng); // ae 0100
   and a5(p5, na, b, nc, nd, e, nf, ng); // be 0101
   and a6(p6, na, nb, c, nd, e, nf ,ng); // ce 0110
   and a7(p7, a, nb, nc, nd, ne, f, ng); // af 0111
   and a8(p8, na, b, nc, nd, ne, f, ng); // bf 1000
   and a9(p9, na, nb, c, nd, ne, f, ng); // cf 1001

   or ov(valid, p0, p1, p2, p3, p4, p5, p6, p7, p8, p9);

   // lsb - msb (wtf is wrong with the order....)
   assign number[0] = p9 | p7 | p5 | p3 | p1 | 2'b0;  // 1, 3, 5, 7, 9
   assign number[1] = p7 | p6 | p3 | p2 | 2'b0;       // 2, 3, 6, 7
   assign number[2] = p7 | p6 | p5 | p4 | 2'b0;       // 4, 5, 6, 7
   assign number[3] = p8 | p9 | 2'b0;                 // 8, 9


   assign number[0] = p9 | p7 | p5 | p3 | p1;  // 1, 3, 5, 7, 9
   assign number[1] = p7 | p6 | p3 | p2;       // 2, 3, 6, 7
   assign number[2] = p7 | p6 | p5 | p4;       // 4, 5, 6, 7
   assign number[3] = p8 | p9;                 // 8, 9

endmodule // keypad

Lab 01/1.2.3/keypad_tb.v
module keypad_test;

   reg a = 0, b = 0, c = 0;
   reg d = 0, e = 0, f = 0, g = 0;
   
   initial begin

      $dumpfile("kp.vcd");  
      $dumpvars(0,keypad_test);
      
      # 10  
    a = 1; d = 1;                // pressing 1
      # 10
    a = 0; b = 1;                // pressing 2
      # 10
    b = 0; c = 1;                // pressing 3
      # 10
    c = 0; d = 0;                
    a = 1; e = 1;                // pressing 4
      # 10
    a = 0; b = 1;                // pressing 5
      # 10
    b = 0; c = 1;                // pressing 6
      # 10
    c = 0; e = 0;                
    a = 1; f = 1;                // pressing 7
      # 10
    a = 0; b = 1;                // pressing 8
      # 10
    b = 0; c = 1;                // pressing 9
      # 10
    c = 0; f = 0;                
    b = 1; g = 1;                // pressing 0
      # 10 
    b = 0; g = 0;                // pressing nothing
      # 10 
      $finish;              // end the simulation
   end                      
   
   wire       valid;
   wire [3:0] number;
   keypad kp (valid, number, a, b, c, d, e, f, g);  

   wire [6:0]   inputs;
   assign inputs = {{ a, b, c, d, e, f, g }};  // this is syntax for grouping signals together as a bus.
           
   initial
     $monitor("abcdefg = %x %x%x%x%x%x%x%x valid = %d number = %b (%d )", inputs, a, b, c, d, e, f, g, valid, number, number);
endmodule // keypad_test

Lab 01/1.2.3/kp.vcd
$date
	Wed Aug 23 22:00:11 2023
$end
$version
	Icarus Verilog
$end
$timescale
	1s
$end
$scope module keypad_test $end
$var wire 1 ! valid $end
$var wire 4 " number [3:0] $end
$var wire 7 # inputs [6:0] $end
$var reg 1 $ a $end
$var reg 1 % b $end
$var reg 1 & c $end
$var reg 1 ' d $end
$var reg 1 ( e $end
$var reg 1 ) f $end
$var reg 1 * g $end
$scope module kp $end
$var wire 1 $ a $end
$var wire 1 % b $end
$var wire 1 & c $end
$var wire 1 ' d $end
$var wire 1 ( e $end
$var wire 1 ) f $end
$var wire 1 * g $end
$var wire 1 + na $end
$var wire 1 , nb $end
$var wire 1 - nc $end
$var wire 1 . nd $end
$var wire 1 / ne $end
$var wire 1 0 nf $end
$var wire 1 1 ng $end
$var wire 1 2 p0 $end
$var wire 1 3 p1 $end
$var wire 1 4 p2 $end
$var wire 1 5 p3 $end
$var wire 1 6 p4 $end
$var wire 1 7 p5 $end
$var wire 1 8 p6 $end
$var wire 1 9 p7 $end
$var wire 1 : p8 $end
$var wire 1 ; p9 $end
$var wire 1 ! valid $end
$var wire 4 < number [3:0] $end
$upscope $end
$upscope $end
$enddefinitions $end
$comment Show the parameter values. $end
$dumpall
$end
#0
$dumpvars
b0 <
0;
0:
09
08
07
06
05
04
03
02
11
10
1/
1.
1-
1,
1+
0*
0)
0(
0'
0&
0%
0$
b0 #
b0 "
0!
$end
#10
b1 "
b1 <
1!
13
0.
0+
1'
b1001000 #
1$
#20
b10 "
b10 <
14
03
0,
1+
1%
b101000 #
0$
#30
b11 "
b11 <
15
04
0-
1,
1&
b11000 #
0%
#40
b100 "
b100 <
16
05
0/
0+
1.
1-
1(
1$
0'
b1000100 #
0&
#50
b101 "
b101 <
17
06
0,
1+
1%
b100100 #
0$
#60
b110 "
b110 <
18
07
0-
1,
1&
b10100 #
0%
#70
b111 "
b111 <
19
08
00
0+
1/
1-
1)
1$
0(
b1000010 #
0&
#80
b1000 "
b1000 <
1:
09
0,
1+
1%
b100010 #
0$
#90
b1001 "
b1001 <
1;
0:
0-
1,
1&
b10010 #
0%
#100
b1000 "
b1000 <
12
0;
01
0,
10
1-
1*
1%
0)
b100001 #
0&
#110
0!
b0 "
b0 <
02
11
1,
0*
b0 #
0%
