Lab 03/3.2/chopUpDigits_lib.v
////////////////////////////////////////////////////////////////////////
//
// Module: regfile
//
// Description:
//   A behavioral MIPS register file.  R0 is hardwired to zero.
//   Given that you won't write behavioral code, don't worry if you don't
//   understand how this works;  We have to use behavioral code (as
//   opposed to the structural code you are writing), because of the
//   latching by the the register file.
//
module regfile (rsData, rtData,
                rsNum, rtNum, rdNum, rdData,
                rdWriteEnable, clock, reset);

   output [31:0] rsData, rtData;
   input  [4:0]  rsNum, rtNum, rdNum;
   input  [31:0] rdData;
   input         rdWriteEnable, clock, reset;

   reg    [31:0] r[0:31];
   integer       i;

   always@(reset)
     if(reset == 1'b1)
       begin
          r[0] <= 32'b0;
          for(i = 1; i <= 31; i = i + 1)
            r[i] <= 32'h00000000;
       end

   assign #1 rsData = r[rsNum];
   assign #1 rtData = r[rtNum];

   wire [31:0] #1 internal_rdData = rdData;     // set up and hold time
   always@(posedge clock)
     begin
        if((reset == 1'b0) && (rdWriteEnable == 1'b1) && (rdNum != 5'b0))
          r[rdNum] <= internal_rdData;
     end

endmodule // regfile_3port

/// Comparator: Compares two values, A and B
//  lt: 1 if A is less than B
//  eq: 1 if A is equal to B
module comparator(lt, eq, A, B);
  parameter
     width = 32;

  output    lt, eq;
  input     [(width-1):0] A, B;
  assign lt = $signed(A) < $signed(B);
  assign eq = $signed(A) == $signed(B);
endmodule

// Here is an implementation of a 2-to-1 multiplexer for you to use
// output = A (when control == 0) or B (when control == 1)
module mux2(out, A, B, control);   // a 2-input multiplexer
   output      out;
   input       A, B;
   input       control;
   wire        wA, wB, not_control;

   not   n1(not_control, control);
   and   a1(wA, A, not_control);
   and   a2(wB, B, control);
   or    o1(out, wA, wB);
endmodule // mux2

Lab 03/3.1/register.v
// register: A register which may be reset to an arbirary value
//
// q      (output) - Current value of register
// d      (input)  - Next value of register
// clk    (input)  - Clock (positive edge-sensitive)
// enable (input)  - Load new value? (yes = 1, no = 0)
// reset  (input)  - Asynchronous reset    (reset = 1)
//
module register(q, d, clk, enable, reset);

    output [31:0] q;
    input  [31:0] d;
    input  clk, enable, reset;

   //  Your implementation goes here
    dffe df0(q[0], d[0], clk, enable, reset);
    dffe df1(q[1], d[1], clk, enable, reset);
    dffe df2(q[2], d[2], clk, enable, reset);
    dffe df3(q[3], d[3], clk, enable, reset);
    dffe df4(q[4], d[4], clk, enable, reset);
    dffe df5(q[5], d[5], clk, enable, reset);
    dffe df6(q[6], d[6], clk, enable, reset);
    dffe df7(q[7], d[7], clk, enable, reset);
    dffe df8(q[8], d[8], clk, enable, reset);
    dffe df9(q[9], d[9], clk, enable, reset);
    dffe df10(q[10], d[10], clk, enable, reset);
    dffe df11(q[11], d[11], clk, enable, reset);
    dffe df12(q[12], d[12], clk, enable, reset);
    dffe df13(q[13], d[13], clk, enable, reset);
    dffe df14(q[14], d[14], clk, enable, reset);
    dffe df15(q[15], d[15], clk, enable, reset);
    dffe df16(q[16], d[16], clk, enable, reset);
    dffe df17(q[17], d[17], clk, enable, reset);
    dffe df18(q[18], d[18], clk, enable, reset);
    dffe df19(q[19], d[19], clk, enable, reset);
    dffe df20(q[20], d[20], clk, enable, reset);
    dffe df21(q[21], d[21], clk, enable, reset);
    dffe df22(q[22], d[22], clk, enable, reset);
    dffe df23(q[23], d[23], clk, enable, reset);
    dffe df24(q[24], d[24], clk, enable, reset);
    dffe df25(q[25], d[25], clk, enable, reset);
    dffe df26(q[26], d[26], clk, enable, reset);
    dffe df27(q[27], d[27], clk, enable, reset);
    dffe df28(q[28], d[28], clk, enable, reset);
    dffe df29(q[29], d[29], clk, enable, reset);
    dffe df30(q[30], d[30], clk, enable, reset);
    dffe df31(q[31], d[31], clk, enable, reset);

endmodule // register



// dffe: D-type flip-flop with enable
//
// q      (output) - Current value of flip flop
// d      (input)  - Next value of flip flop
// clk    (input)  - Clock (positive edge-sensitive)
// enable (input)  - Load new value? (yes = 1, no = 0)
// reset  (input)  - Asynchronous reset   (reset =  1)
//
module dffe(q, d, clk, enable, reset);
   output q;
   reg    q;
   input  d;
   input  clk, enable, reset;

   always@(reset)
     if (reset == 1'b1)
       q <= 0;

   always@(posedge clk)
     if ((reset == 1'b0) && (enable == 1'b1))
       q <= d;
endmodule // dffe

Lab 03/3.1/reg_writer.v
module reg_writer(regnum, done, go, direction, clock, reset);

	input direction, go;
	input clock, reset;

	output done;
	output [4:0] regnum;

	wire sGarbage, sStart, sUp1, sUp2, sUp3, sUp4, sDown1, sDown2, sDown3, sDown4, sDone;


	wire sGarbage_next = (sGarbage & ~go) | reset;
	wire sStart_next = ((sStart & go) | (sGarbage & go) | (sDone & go)) & ~reset;

	wire sUp1_next = (sStart & (direction & ~go)) & ~reset;
	wire sUp2_next = sUp1 & ~reset;
	wire sUp3_next = sUp2 & ~reset;
	wire sUp4_next = sUp3 & ~reset;

	wire sDown1_next = (sStart & (~direction & ~go)) & ~reset;
	wire sDown2_next = sDown1 & ~reset;
	wire sDown3_next = sDown2 & ~reset;
	wire sDown4_next = sDown3 & ~reset;


	wire sDone_next = ((sUp4 | sDown4)  | (sDone & ~go)) & ~reset;

	dffe fsGarbage(sGarbage, sGarbage_next, clock, 1'b1, 1'b0);
	dffe fsStart(sStart, sStart_next, clock, 1'b1, 1'b0);

	dffe fsUp1(sUp1, sUp1_next, clock, 1'b1, 1'b0);
	dffe fsUp2(sUp2, sUp2_next, clock, 1'b1, 1'b0);
	dffe fsUp3(sUp3, sUp3_next, clock, 1'b1, 1'b0);
	dffe fsUp4(sUp4, sUp4_next, clock, 1'b1, 1'b0);

	dffe fsDown1(sDown1, sDown1_next, clock, 1'b1, 1'b0);
	dffe fsDown2(sDown2, sDown2_next, clock, 1'b1, 1'b0);
	dffe fsDown3(sDown3, sDown3_next, clock, 1'b1, 1'b0);
	dffe fsDown4(sDown4, sDown4_next, clock, 1'b1, 1'b0);

	dffe fsDone(sDone, sDone_next, clock, 1'b1, 1'b0);

	assign done = sDone;
	assign regnum = 
			sDone ? 0:
			sUp4   ? 12:
			sDown4 ? 4 :
			sDown3 ? 5 :
			sUp3   ? 11:
			sUp2   ? 10:
			sDown2 ? 6 :
			sDown1 ? 7 :
			sUp1   ? 9 :
			sStart ? 8 :
			0;
endmodule // end reg_writer

Lab 03/3.1/reg_writer_tb.v
module reg_writer_test;
    reg       clock = 0;
    always #1 clock = !clock;

    reg go = 0;
    reg reset = 1;
    reg direction = 0;
    reg [31:0] data;
    wire done;
    wire [4:0] regnum;
    integer i;

    wire [31:0] writtenValue;
    reg_writer writer(regnum, done, go, direction, clock, reset);
    regfile rf (, , , , regnum, data, ~done, clock, reset);

    initial begin
        $dumpfile("reg_writer.vcd");
        $dumpvars(0, reg_writer_test);
        # 2      reset = 0;

	// Test writing down
	# 2 go = 1; data = 32'hd00; direction = 0;
	# 2 go = 0; data = 32'hd01;
	# 2 data = 32'hd02;
	# 2 data = 32'hd03;
	# 2 data = 32'hd04;
	# 2 data = 32'hd05;

	# 6 // Finish our run

    // Print contents of registers 3-13 to the terminal
    $display ( "First Run" );
    $display ( "Dumping register state: " );
    $display ( "  Register :  hex-value (  dec-value )" );
    for (i = 3 ; i < 14 ; i = i + 1)
        $display ( "%d: 0x%x ( %d )", i, rf.r[i], rf.r[i]);
    $display ( "%d: 0x%x ( %d )", 0, rf.r[0], rf.r[0]);
    


	# 2 reset = 1; // Reset the machine
	# 2 reset = 0;

	// Test writing up
	# 2 go = 1; data = 32'hdFF; direction = 1;
	# 2 go = 0; data = 32'hdFE;
	# 2 data = 32'hdFD;
	# 2 data = 32'hdFC;
	# 2 data = 32'hdFB;
	# 2 data = 32'hdFA;

    #6  // Finish a run

    // Print contents of registers 3-13 to the terminal
    $display ( "Second Run" );
    $display ( "  Register :  hex-value (  dec-value )" );
    for (i = 4 ; i < 14 ; i = i + 1)
        $display ( "%d: 0x%x ( %d )", i, rf.r[i], rf.r[i]);
    $display ( "%d: 0x%x ( %d )", 0, rf.r[0], rf.r[0]);
    $display ( "Done.  Simulation ending." );

    // Add your own testcases here!

    $finish;
    end

endmodule

Lab 03/3.1/reg_writer.vcd
$date
	Tue Sep  5 14:25:44 2023
$end
$version
	Icarus Verilog
$end
$timescale
	1s
$end
$scope module reg_writer_test $end
$var wire 5 ! regnum [4:0] $end
$var wire 1 " done $end
$var reg 1 # clock $end
$var reg 32 $ data [31:0] $end
$var reg 1 % direction $end
$var reg 1 & go $end
$var reg 1 ' reset $end
$var integer 32 ( i [31:0] $end
$scope module rf $end
$var wire 1 # clock $end
$var wire 32 ) internal_rdData [31:0] $end
$var wire 32 * rdData [31:0] $end
$var wire 1 + rdWriteEnable $end
$var wire 1 ' reset $end
$var wire 32 , rsData [31:0] $end
$var wire 5 - rsNum [4:0] $end
$var wire 32 . rtData [31:0] $end
$var wire 5 / rtNum [4:0] $end
$var wire 5 0 rdNum [4:0] $end
$var integer 32 1 i [31:0] $end
$upscope $end
$scope module writer $end
$var wire 1 # clock $end
$var wire 1 % direction $end
$var wire 1 " done $end
$var wire 1 & go $end
$var wire 1 ' reset $end
$var wire 1 2 sDone_next $end
$var wire 1 3 sDown1_next $end
$var wire 1 4 sDown2_next $end
$var wire 1 5 sDown3_next $end
$var wire 1 6 sDown4_next $end
$var wire 1 7 sGarbage_next $end
$var wire 1 8 sStart_next $end
$var wire 1 9 sUp1_next $end
$var wire 1 : sUp2_next $end
$var wire 1 ; sUp3_next $end
$var wire 1 < sUp4_next $end
$var wire 1 = sUp4 $end
$var wire 1 > sUp3 $end
$var wire 1 ? sUp2 $end
$var wire 1 @ sUp1 $end
$var wire 1 A sStart $end
$var wire 1 B sGarbage $end
$var wire 1 C sDown4 $end
$var wire 1 D sDown3 $end
$var wire 1 E sDown2 $end
$var wire 1 F sDown1 $end
$var wire 1 G sDone $end
$var wire 5 H regnum [4:0] $end
$scope module fsDone $end
$var wire 1 # clk $end
$var wire 1 2 d $end
$var wire 1 I enable $end
$var wire 1 J reset $end
$var reg 1 G q $end
$upscope $end
$scope module fsDown1 $end
$var wire 1 # clk $end
$var wire 1 3 d $end
$var wire 1 K enable $end
$var wire 1 L reset $end
$var reg 1 F q $end
$upscope $end
$scope module fsDown2 $end
$var wire 1 # clk $end
$var wire 1 4 d $end
$var wire 1 M enable $end
$var wire 1 N reset $end
$var reg 1 E q $end
$upscope $end
$scope module fsDown3 $end
$var wire 1 # clk $end
$var wire 1 5 d $end
$var wire 1 O enable $end
$var wire 1 P reset $end
$var reg 1 D q $end
$upscope $end
$scope module fsDown4 $end
$var wire 1 # clk $end
$var wire 1 6 d $end
$var wire 1 Q enable $end
$var wire 1 R reset $end
$var reg 1 C q $end
$upscope $end
$scope module fsGarbage $end
$var wire 1 # clk $end
$var wire 1 7 d $end
$var wire 1 S enable $end
$var wire 1 T reset $end
$var reg 1 B q $end
$upscope $end
$scope module fsStart $end
$var wire 1 # clk $end
$var wire 1 8 d $end
$var wire 1 U enable $end
$var wire 1 V reset $end
$var reg 1 A q $end
$upscope $end
$scope module fsUp1 $end
$var wire 1 # clk $end
$var wire 1 9 d $end
$var wire 1 W enable $end
$var wire 1 X reset $end
$var reg 1 @ q $end
$upscope $end
$scope module fsUp2 $end
$var wire 1 # clk $end
$var wire 1 : d $end
$var wire 1 Y enable $end
$var wire 1 Z reset $end
$var reg 1 ? q $end
$upscope $end
$scope module fsUp3 $end
$var wire 1 # clk $end
$var wire 1 ; d $end
$var wire 1 [ enable $end
$var wire 1 \ reset $end
$var reg 1 > q $end
$upscope $end
$scope module fsUp4 $end
$var wire 1 # clk $end
$var wire 1 < d $end
$var wire 1 ] enable $end
$var wire 1 ^ reset $end
$var reg 1 = q $end
$upscope $end
$upscope $end
$upscope $end
$enddefinitions $end
$comment Show the parameter values. $end
$dumpall
$end
#0
$dumpvars
0^
1]
0\
1[
0Z
1Y
0X
1W
0V
1U
0T
1S
0R
1Q
0P
1O
0N
1M
0L
1K
0J
1I
b0xxxx H
xG
xF
xE
xD
xC
xB
xA
x@
x?
x>
x=
0<
0;
0:
09
08
17
06
05
04
03
02
b100000 1
b0xxxx 0
bz /
bx .
bz -
bx ,
x+
bx *
bx )
bx (
1'
0&
0%
bx $
0#
x"
b0xxxx !
$end
#1
b0 !
b0 0
b0 H
1+
1B
0A
0@
0?
0>
0=
0F
0E
0D
0C
0"
0G
1#
#2
0#
0'
#3
1#
#4
18
07
0#
b110100000000 $
b110100000000 *
1&
#5
b1000 !
b1000 0
b1000 H
0B
1A
1#
b110100000000 )
#6
08
13
0#
b110100000001 $
b110100000001 *
0&
#7
b111 !
b111 0
b111 H
03
14
1F
0A
1#
b110100000001 )
#8
0#
b110100000010 $
b110100000010 *
#9
b110 !
b110 0
b110 H
04
15
0F
1E
1#
b110100000010 )
#10
0#
b110100000011 $
b110100000011 *
#11
b101 !
b101 0
b101 H
16
05
1D
0E
1#
b110100000011 )
#12
0#
b110100000100 $
b110100000100 *
#13
b100 !
b100 0
b100 H
12
06
0D
1C
1#
b110100000100 )
#14
0#
b110100000101 $
b110100000101 *
#15
b0 !
b0 0
b0 H
0+
1"
1G
0C
1#
b110100000101 )
#16
0#
#17
1#
#18
0#
#19
1#
#20
0#
b1110 (
#21
1#
#22
02
b100000 1
17
0#
1'
#23
1+
0"
0G
1B
1#
#24
0#
0'
#25
1#
#26
18
07
0#
1%
b110111111111 $
b110111111111 *
1&
#27
b1000 !
b1000 0
b1000 H
1A
0B
1#
b110111111111 )
#28
08
19
0#
b110111111110 $
b110111111110 *
0&
#29
b1001 !
b1001 0
b1001 H
09
1:
0A
1@
1#
b110111111110 )
#30
0#
b110111111101 $
b110111111101 *
#31
b1010 !
b1010 0
b1010 H
1;
0:
1?
0@
1#
b110111111101 )
#32
0#
b110111111100 $
b110111111100 *
#33
b1011 !
b1011 0
b1011 H
0;
1<
0?
1>
1#
b110111111100 )
#34
0#
b110111111011 $
b110111111011 *
#35
12
b1100 !
b1100 0
b1100 H
0<
1=
0>
1#
b110111111011 )
#36
0#
b110111111010 $
b110111111010 *
#37
b0 !
b0 0
b0 H
0+
0=
1"
1G
1#
b110111111010 )
#38
0#
#39
1#
#40
0#
#41
1#
#42
0#
b1110 (
