Lab 02/2.2.1/alu1.v
module full_adder(sum, cout, a, b, cin);
    output sum, cout;
    input  a, b, cin;
    wire   partial_s, partial_c1, partial_c2;

    xor x0(partial_s, a, b);
    xor x1(sum, partial_s, cin);
    and a0(partial_c1, a, b);
    and a1(partial_c2, partial_s, cin);
    or  o1(cout, partial_c1, partial_c2);
endmodule // full_adder

module logic_unit(out, A, B, C, D, control);
    output out;
    input A, B, C, D;
    input [1:0] control;

    wire wA, wB, wC, wD;

    assign wA = A & (control == 2'b00);
    assign wB = B & (control == 2'b01);
    assign wC = C & (control == 2'b10);
    assign wD = D & (control == 2'b11);

    or o1(out, wA, wB, wC, wD);

endmodule // logic_unit

`define ALU_ADD    3'h2
`define ALU_SUB    3'h3
`define ALU_AND    3'h4
`define ALU_OR     3'h5
`define ALU_NOR    3'h6
`define ALU_XOR    3'h7

// 01x -> arithmetic, 1xx -> logic
module alu1(out, carryout, A, B, carryin, control);
    output      out, carryout;
    input       A, B, carryin;
    input [2:0] control;

    // add code here!!!
    wire w_adder, w_logic;

    // full adder part
    wire adder_B;
    xor x1(adder_B, B, control[0]);

    // assign neg_B = (control == `ALU_SUB) ? ~B : B;
    // assign carryin_mod = (control == `ALU_SUB) ? 1'b1 : carryin;
    
    full_adder adder1(w_adder, carryout, A, adder_B, carryin);

    // logical unit part
    wire A_and_B, A_or_B, A_nor_B, A_xor_B;
    and and1(A_and_B, A, B);
    or or1(A_or_B, A, B);
    nor nor1(A_nor_B, A, B);
    xor xor1(A_xor_B, A, B);

    logic_unit l1(w_logic, A_and_B, A_or_B, A_nor_B, A_xor_B, control[1:0]);

    // wire w_adder_out, w_logic_out;
    // assign w_adder_out = w_adder & (control[2:1] == 2'b01);
    // assign w_logic_out = w_logic & (control[2] == 1'b1);
    
    // or o1(out, w_adder_out, w_logic_out);

    assign out = (control[2] == 1'b1) ? w_logic : w_adder;
   
endmodule // alu1

Lab 02/2.2.1/alu1_tb.v
module alu1_test;
    // exhaustively test your 1-bit ALU implementation by 
    // adapting mux4_tb.v from Lab 2 part 1
    //   these are inputs to "logicunit under test"
    reg A = 0;
    reg B = 0;
    reg carryin = 0;
    reg expect_out = 0;
    reg expect_cout = 0;

    reg [2:0] control;
    
    // wires for the outputs of "logicunit under test"
    wire out, carryout;
    
    // the circuit under test
    alu1 a1(out, carryout, A, B, carryin, control);
    
    initial begin               // initial = run at beginning of simulation
                                // begin/end = associate block with initial

        $dumpfile("alu1.vcd");
        $dumpvars(0, alu1_test);

        $display(" -------- logic unit -------- ");
        A = 0; B = 0; control = 3'b100; expect_out = 0; #4 // 0
        A = 0; B = 1; control = 3'b100; expect_out = 0; #4 // 0
        A = 1; B = 0; control = 3'b100; expect_out = 0; #4 // 0
        A = 1; B = 1; control = 3'b100; expect_out = 1; #4 // 1
        
        A = 0; B = 0; control = 3'b101; expect_out = 0; #4 // 0
        A = 0; B = 1; control = 3'b101; expect_out = 1; #4 // 1
        A = 1; B = 0; control = 3'b101; expect_out = 1; #4 // 1
        A = 1; B = 1; control = 3'b101; expect_out = 1; #4 // 1
        
        A = 0; B = 0; control = 3'b110; expect_out = 1; #4 // 1
        A = 0; B = 1; control = 3'b110; expect_out = 0; #4 // 0
        A = 1; B = 0; control = 3'b110; expect_out = 0; #4 // 0
        A = 1; B = 1; control = 3'b110; expect_out = 0; #4 // 0
    
        A = 0; B = 0; control = 3'b111; expect_out = 0; #4 // 0
        A = 0; B = 1; control = 3'b111; expect_out = 1; #4 // 1
        A = 1; B = 0; control = 3'b111; expect_out = 1; #4 // 1
        A = 1; B = 1; control = 3'b111; expect_out = 0; #4 // 0

        $display();
        $display(" -------- full adder -------- ");
        $display("A   B   Cin   Control     Out   Cout   | expect_out   expect_cout");

        A = 0; B = 0; carryin = 0; control = 3'b010; expect_out = 0; expect_cout = 0; #4 // 0 0 
        A = 0; B = 0; carryin = 1; control = 3'b010; expect_out = 1; expect_cout = 0; #4 // 1 0

        A = 0; B = 1; carryin = 0; control = 3'b010; expect_out = 1; expect_cout = 0; #4 // 1 0
        A = 0; B = 1; carryin = 1; control = 3'b010; expect_out = 0; expect_cout = 1; #4 // 0 1
        
        A = 1; B = 0; carryin = 0; control = 3'b010; expect_out = 1; expect_cout = 0; #4 // 1 0
        A = 1; B = 0; carryin = 1; control = 3'b010; expect_out = 0; expect_cout = 1; #4 // 0 1

        A = 1; B = 1; carryin = 0; control = 3'b010; expect_out = 0; expect_cout = 1; #4 // 0 1
        A = 1; B = 1; carryin = 1; control = 3'b010; expect_out = 1; expect_cout = 1; #4 // 1 1

        $display(" -------- complement full adder -------- ");
        $display("A   B   Cin   Control     Out   Cout   | expect_out   expect_cout");

        A = 0; B = 0; carryin = 0; control = 3'b011; expect_out = 0; expect_cout = 0; #4 // 0 0 
        A = 0; B = 0; carryin = 1; control = 3'b011; expect_out = 1; expect_cout = 0; #4 // 1 0

        A = 0; B = 1; carryin = 0; control = 3'b011; expect_out = 1; expect_cout = 0; #4 // 1 0
        A = 0; B = 1; carryin = 1; control = 3'b011; expect_out = 0; expect_cout = 1; #4 // 0 1
        
        A = 1; B = 0; carryin = 0; control = 3'b011; expect_out = 1; expect_cout = 0; #4 // 1 0
        A = 1; B = 0; carryin = 1; control = 3'b011; expect_out = 0; expect_cout = 1; #4 // 0 1

        A = 1; B = 1; carryin = 0; control = 3'b011; expect_out = 0; expect_cout = 1; #4 // 0 1
        A = 1; B = 1; carryin = 1; control = 3'b011; expect_out = 1; expect_cout = 1; #4 // 1 1

        $finish; // end the simulation
    end  
   
    initial begin
        $display("A   B   Cin   Control     Out   Cout   |  expect_out   expect_cout");
        $monitor("A=%b B=%b Cin=%b Control=%b Out=%b Cout=%b | %b %b", A, B, carryin, control, out, carryout, expect_out, expect_cout);
    end

endmodule

Lab 02/2.2.1/alu1.vcd
$date
	Thu Aug 31 16:09:39 2023
$end
$version
	Icarus Verilog
$end
$timescale
	1s
$end
$scope module alu1_test $end
$var wire 1 ! out $end
$var wire 1 " carryout $end
$var reg 1 # A $end
$var reg 1 $ B $end
$var reg 1 % carryin $end
$var reg 3 & control [2:0] $end
$var reg 1 ' expect_cout $end
$var reg 1 ( expect_out $end
$scope module a1 $end
$var wire 1 # A $end
$var wire 1 ) A_and_B $end
$var wire 1 * A_nor_B $end
$var wire 1 + A_or_B $end
$var wire 1 , A_xor_B $end
$var wire 1 $ B $end
$var wire 1 - adder_B $end
$var wire 1 % carryin $end
$var wire 3 . control [2:0] $end
$var wire 1 / w_logic $end
$var wire 1 0 w_adder $end
$var wire 1 ! out $end
$var wire 1 " carryout $end
$scope module adder1 $end
$var wire 1 # a $end
$var wire 1 - b $end
$var wire 1 % cin $end
$var wire 1 " cout $end
$var wire 1 1 partial_c1 $end
$var wire 1 2 partial_c2 $end
$var wire 1 3 partial_s $end
$var wire 1 0 sum $end
$upscope $end
$scope module l1 $end
$var wire 1 ) A $end
$var wire 1 + B $end
$var wire 1 * C $end
$var wire 1 , D $end
$var wire 2 4 control [1:0] $end
$var wire 1 / out $end
$var wire 1 5 wA $end
$var wire 1 6 wB $end
$var wire 1 7 wC $end
$var wire 1 8 wD $end
$upscope $end
$upscope $end
$upscope $end
$enddefinitions $end
$comment Show the parameter values. $end
$dumpall
$end
#0
$dumpvars
08
07
06
05
b0 4
03
02
01
00
0/
b100 .
0-
0,
0+
1*
0)
0(
0'
b100 &
0%
0$
0#
0"
0!
$end
#4
10
13
1-
1+
0*
1,
1$
#8
10
0"
0-
13
01
0$
1#
#12
1!
00
1"
1/
03
11
15
1-
1)
0,
1(
1$
#16
0!
0/
05
10
0"
b1 4
1-
0)
0+
1*
13
01
0(
b101 &
b101 .
0$
0#
#20
1!
00
1/
03
16
0-
1+
0*
1,
1(
1$
#24
1"
11
00
1-
03
0$
1#
#28
10
0"
13
01
0-
1)
0,
1$
#32
06
17
00
b10 4
0-
0)
0+
1*
03
b110 &
b110 .
0$
0#
#36
0!
10
0/
13
07
1-
1+
0*
1,
0(
1$
#40
10
0"
0-
13
01
0$
1#
#44
00
1"
03
11
1-
1)
0,
1$
#48
10
0"
b11 4
1-
0)
0+
1*
13
01
b111 &
b111 .
0$
0#
#52
1!
00
1/
03
18
0-
1+
0*
1,
1(
1$
#56
1"
11
00
1-
03
0$
1#
#60
0!
10
0"
0/
13
01
08
0-
1)
0,
0(
1$
#64
0!
1/
17
00
b10 4
0-
0)
0+
1*
03
b10 &
b10 .
0$
0#
#68
1!
10
1(
1%
#72
0/
1!
13
07
10
1-
1+
0*
1,
0%
1$
#76
0!
1"
00
12
1'
0(
1%
#80
1!
10
0"
02
0-
13
01
0'
1(
0%
0$
1#
#84
0!
1"
00
12
1'
0(
1%
#88
0!
03
11
00
02
1-
1)
0,
0%
1$
#92
1!
10
1(
1%
#96
1!
10
0"
b11 4
1-
0)
0+
1*
13
01
0'
0(
b11 &
b11 .
0%
0$
0#
#100
0!
1"
00
12
1(
1%
#104
1/
0!
0"
03
18
00
02
0-
1+
0*
1,
0%
1$
#108
1!
10
1'
0(
1%
#112
0!
00
1"
11
1-
03
0'
1(
0%
0$
1#
#116
1!
10
1'
0(
1%
#120
0"
0/
1!
13
01
08
10
0-
1)
0,
0%
1$
#124
0!
1"
00
12
1(
1%
