Lab 03/3.2/register.v
// register: A register which may be reset to an arbirary value
//
// q      (output) - Current value of register
// d      (input)  - Next value of register
// clk    (input)  - Clock (positive edge-sensitive)
// enable (input)  - Load new value? (yes = 1, no = 0)
// reset  (input)  - Asynchronous reset    (reset = 1)
//
module register(q, d, clk, enable, reset);

    output [31:0] q;
    input  [31:0] d;
    input  clk, enable, reset;

   //  Your implementation goes here

endmodule // register



// dffe: D-type flip-flop with enable
//
// q      (output) - Current value of flip flop
// d      (input)  - Next value of flip flop
// clk    (input)  - Clock (positive edge-sensitive)
// enable (input)  - Load new value? (yes = 1, no = 0)
// reset  (input)  - Asynchronous reset   (reset =  1)
//
module dffe(q, d, clk, enable, reset);
   output q;
   reg    q;
   input  d;
   input  clk, enable, reset;

   always@(reset)
     if (reset == 1'b1)
       q <= 0;

   always@(posedge clk)
     if ((reset == 1'b0) && (enable == 1'b1))
       q <= d;
endmodule // dffe

Lab 03/3.2/chopUpDigits_control.v

module chopUpDigits_control (done, get_new, load_index, load_number, select_base, write, base, number_is_0, go, clk, reset);
	output done, get_new, load_index, load_number, select_base, write;
	input base, number_is_0, go;
	input clk, reset;

	assign temp_base = base;
	assign temp_go = go;

	wire sGarbage, sStart, sWhile8, sWhile16, sWrite8, sWrite16, sDone;

	wire sGarbage_next = (sGarbage & ~temp_go) | reset;
	wire sStart_next = ((sGarbage & temp_go) | (sStart & temp_go) | (sDone & temp_go)) & ~reset;
	wire sWhile8_next = ((sStart & (~temp_go & ~temp_base)) | sWrite8) & ~reset;
	wire sWhile16_next = ((sStart & (~temp_go & temp_base)) | sWrite16) & ~reset;
	wire sWrite8_next = (sWhile8 & ~number_is_0) & ~reset;
	wire sWrite16_next = (sWhile16 & ~number_is_0) & ~reset;
	wire sDone_next = ((sWhile8 & number_is_0) | (sWhile16 & number_is_0) | (sDone & ~temp_go)) & ~reset;

	dffe fsGarbage(sGarbage, sGarbage_next, clk, 1'b1, 1'b0);
	dffe fsStart(sStart, sStart_next, clk, 1'b1, 1'b0);
	dffe fsWhile8(sWhile8, sWhile8_next, clk, 1'b1, 1'b0);
	dffe fsWhile16(sWhile16, sWhile16_next, clk, 1'b1, 1'b0);
	dffe fsWrite8(sWrite8, sWrite8_next, clk, 1'b1, 1'b0);
	dffe fsWrite16(sWrite16, sWrite16_next, clk, 1'b1, 1'b0);
	dffe fsDone(sDone, sDone_next, clk, 1'b1, 1'b0);

	assign load_number = (sStart | sWrite8 | sWrite16);
	assign load_index = (sStart | sWrite8 | sWrite16);
	assign get_new = sStart;
    assign select_base = temp_base;
    assign write = (sWrite8 | sWrite16);

	// chopUpDigits_circuit c1(number_is_0, get_new, load_index, load_number, select_temp_base, write, number, digits_ptr, clk, reset);
	assign done = sDone;
endmodule

Lab 03/3.2/chopUpDigits_lib.v
////////////////////////////////////////////////////////////////////////
//
// Module: regfile
//
// Description:
//   A behavioral MIPS register file.  R0 is hardwired to zero.
//   Given that you won't write behavioral code, don't worry if you don't
//   understand how this works;  We have to use behavioral code (as
//   opposed to the structural code you are writing), because of the
//   latching by the the register file.
//
module regfile (rsData, rtData,
                rsNum, rtNum, rdNum, rdData,
                rdWriteEnable, clock, reset);

   output [31:0] rsData, rtData;
   input  [4:0]  rsNum, rtNum, rdNum;
   input  [31:0] rdData;
   input         rdWriteEnable, clock, reset;

   reg    [31:0] r[0:31];
   integer       i;

   always@(reset)
     if(reset == 1'b1)
       begin
          r[0] <= 32'b0;
          for(i = 1; i <= 31; i = i + 1)
            r[i] <= 32'h00000000;
       end

   assign #1 rsData = r[rsNum];
   assign #1 rtData = r[rtNum];

   wire [31:0] #1 internal_rdData = rdData;     // set up and hold time
   always@(posedge clock)
     begin
        if((reset == 1'b0) && (rdWriteEnable == 1'b1) && (rdNum != 5'b0))
          r[rdNum] <= internal_rdData;
     end

endmodule // regfile_3port

/// Comparator: Compares two values, A and B
//  lt: 1 if A is less than B
//  eq: 1 if A is equal to B
module comparator(lt, eq, A, B);
  parameter
     width = 32;

  output    lt, eq;
  input     [(width-1):0] A, B;
  assign lt = $signed(A) < $signed(B);
  assign eq = $signed(A) == $signed(B);
endmodule

// Here is an implementation of a 2-to-1 multiplexer for you to use
// output = A (when control == 0) or B (when control == 1)
module mux2(out, A, B, control);   // a 2-input multiplexer
   output      out;
   input       A, B;
   input       control;
   wire        wA, wB, not_control;

   not   n1(not_control, control);
   and   a1(wA, A, not_control);
   and   a2(wB, B, control);
   or    o1(out, wA, wB);
endmodule // mux2

Lab 03/3.2/chopUpDigits_circuit.v
`define ALU_ADD    3'h0
`define ALU_SUB    3'h1

// chopUpDigits datapath
module chopUpDigits_circuit(number_is_0, get_new, load_index, load_number, select_base, write, number, digits_ptr, clk, reset);
	output number_is_0;
	input get_new, load_index, load_number, select_base, write;
	input [31:0] number;
	input [4:0] digits_ptr;
	input clk, reset;

	reg [31:0]  number_reg;
	reg [4:0] digits_ptr_reg, index_reg;

	wire [31:0] div_8 = {3'b0, number_reg[31:3]};
	wire [31:0] mod_8 = {29'b0, number_reg[2:0]};
	wire [31:0] div_16 = {4'b0, number_reg[31:4]};
	wire [31:0] mod_16 = {28'b0, number_reg[3:0]};

	always@(posedge clk)
	begin
		if (reset == 1'b1)
			begin
				number_reg <= 0;
				digits_ptr_reg <= 0;
				index_reg <= 0;
			end
		else
			begin
				if(~reset && get_new)
				begin
					digits_ptr_reg <= digits_ptr;
				end

				if(~reset && load_number && get_new)
				begin
					number_reg <= number;
				end

				if(~reset && load_number && ~get_new && ~select_base)
				begin
					number_reg <= div_8;
				end

				if(~reset && load_number && ~get_new && select_base)
				begin
					number_reg <= div_16;
				end

				if(~reset && load_index && get_new)
				begin
					index_reg <= 0;
				end

				if (~reset && load_index && ~get_new)
				begin
					index_reg <= index_reg + 1;
				end
			end
		end

	wire [4:0] digit_ptr_plus_index;
	wire [31:0] write_data;
	
	assign write_data = select_base ? mod_16 : mod_8;
	assign digit_ptr_plus_index = digits_ptr_reg + index_reg;
	regfile rf( , , , , digit_ptr_plus_index, write_data, write, clk, reset);

	comparator #(32) compareNumber( , number_is_0, number_reg, 32'b0);

endmodule

Lab 03/3.2/chopUpDigits_control_tb.v
module chopUpDigits_control_test;
    reg       clk = 0;
    always #1 clk = !clk;  // Do not reduce below 2.

    reg go = 0;
    reg reset = 1;
    reg[31:0] number;
    reg base;
    reg [4:0] digits_ptr;

    integer i;

    wire number_is_0; // chopUpDigits_circuit's output
    wire done, get_new, load_index, load_number, select_base, write; // chopUpDigits_control's output
    chopUpDigits_circuit circuit(number_is_0, get_new, load_index, load_number, select_base, write, number, digits_ptr, clk, reset);
    chopUpDigits_control control(done, get_new, load_index, load_number, select_base, write, base, number_is_0, go, clk, reset);

    initial begin
        $dumpfile("chopUpDigits_control.vcd");
        $dumpvars(0, chopUpDigits_control_test);

        #2      reset = 0;

        // Test 1: Chop 0
        $display("\n\nTest 1: o0, base 8");

        for ( i = 0; i < 32; i = i + 1)
          circuit.rf.r[i] <= 99;

        # 2  go = 1;
             number = 32'o0;
             digits_ptr = 15;
             base = 0;

      	# 2  go = 0;
        # 20
        for ( i = 14; i < 23; i = i + 1)
          $display("i = %d, value = %d", i, $signed(circuit.rf.r[i]));



        // Test 2: Chop hex
        $display("\n\nTest 2: 0x12340, base 16");

        #2
        for ( i = 0; i < 32; i = i + 1)
          circuit.rf.r[i] <= 99;

        # 2  go = 1;
             number = 32'h12340;
             digits_ptr = 15;
             base = 1;

        # 100
        for ( i = 14; i < 23; i = i + 1)
          $display("i = %d, value = %d", i, $signed(circuit.rf.r[i]));


        // Test 2.5: Chop hex
        $display("\n\nTest 2.5: 0x123456, base 16");

        #2
        for ( i = 0; i < 32; i = i + 1)
          circuit.rf.r[i] <= 99;

        # 2  go = 1;
             number = 32'h123456;
             digits_ptr = 15;
             reset = 1;
             base = 1;

      	# 2  go = 1;
             number = 32'h122226;
             digits_ptr = 15;
             base = 1;
        # 100
        for ( i = 14; i < 23; i = i + 1)
          $display("i = %d, value = %d", i, $signed(circuit.rf.r[i]));  


        // Test 3: Mid run base change
        $display("\n\nTest 3: 0x5678912 , base 16");

        #2
        for ( i = 0; i < 32; i = i + 1)
          circuit.rf.r[i] <= 99;

        # 2  go = 1;
             number = 32'h5678912;
             digits_ptr = 15;
             base = 1;

        # 2  go = 0;
        # 2  base = 0;
        # 100
        for ( i = 14; i < 26; i = i + 1)
          $display("i = %d, value = %d", i, $signed(circuit.rf.r[i]));

        #10 $finish;
    end

    initial begin
        $monitor("done = %d", done);

        // You can also explore wires inside the modules. For example to
        // monitor value of write_data wire inside the circuit, in addition
        // to done signal, you should change the monitor statement to:
        // $monitor("done = %d, write_data = %d", done, circuit.write_data);

        // It is best to monitor only the signals that you are exploring at a particular time.
        // FOR DEBUGGING: It will be really useful to monitor your states inside the control module.
    end

endmodule

Lab 03/3.2/chopUpDigits_control.vcd
$date
	Thu Sep  7 18:43:39 2023
$end
$version
	Icarus Verilog
$end
$timescale
	1s
$end
$scope module chopUpDigits_control_test $end
$var wire 1 ! write $end
$var wire 1 " select_base $end
$var wire 1 # number_is_0 $end
$var wire 1 $ load_number $end
$var wire 1 % load_index $end
$var wire 1 & get_new $end
$var wire 1 ' done $end
$var reg 1 ( base $end
$var reg 1 ) clk $end
$var reg 5 * digits_ptr [4:0] $end
$var reg 1 + go $end
$var reg 32 , number [31:0] $end
$var reg 1 - reset $end
$var integer 32 . i [31:0] $end
$scope module circuit $end
$var wire 1 ) clk $end
$var wire 5 / digits_ptr [4:0] $end
$var wire 32 0 number [31:0] $end
$var wire 1 - reset $end
$var wire 32 1 write_data [31:0] $end
$var wire 1 ! write $end
$var wire 1 " select_base $end
$var wire 1 # number_is_0 $end
$var wire 32 2 mod_8 [31:0] $end
$var wire 32 3 mod_16 [31:0] $end
$var wire 1 $ load_number $end
$var wire 1 % load_index $end
$var wire 1 & get_new $end
$var wire 32 4 div_8 [31:0] $end
$var wire 32 5 div_16 [31:0] $end
$var wire 5 6 digit_ptr_plus_index [4:0] $end
$var reg 5 7 digits_ptr_reg [4:0] $end
$var reg 5 8 index_reg [4:0] $end
$var reg 32 9 number_reg [31:0] $end
$scope module compareNumber $end
$var wire 32 : A [31:0] $end
$var wire 32 ; B [31:0] $end
$var wire 1 < lt $end
$var wire 1 # eq $end
$var parameter 32 = width $end
$upscope $end
$scope module rf $end
$var wire 1 ) clock $end
$var wire 32 > internal_rdData [31:0] $end
$var wire 32 ? rdData [31:0] $end
$var wire 5 @ rdNum [4:0] $end
$var wire 1 - reset $end
$var wire 32 A rsData [31:0] $end
$var wire 5 B rsNum [4:0] $end
$var wire 32 C rtData [31:0] $end
$var wire 5 D rtNum [4:0] $end
$var wire 1 ! rdWriteEnable $end
$var integer 32 E i [31:0] $end
$upscope $end
$upscope $end
$scope module control $end
$var wire 1 ( base $end
$var wire 1 ) clk $end
$var wire 1 ' done $end
$var wire 1 & get_new $end
$var wire 1 + go $end
$var wire 1 % load_index $end
$var wire 1 $ load_number $end
$var wire 1 # number_is_0 $end
$var wire 1 - reset $end
$var wire 1 F sDone_next $end
$var wire 1 G sGarbage_next $end
$var wire 1 H sStart_next $end
$var wire 1 I sWhile16_next $end
$var wire 1 J sWhile8_next $end
$var wire 1 K sWrite16_next $end
$var wire 1 L sWrite8_next $end
$var wire 1 " select_base $end
$var wire 1 M temp_base $end
$var wire 1 N temp_go $end
$var wire 1 ! write $end
$var wire 1 O sWrite8 $end
$var wire 1 P sWrite16 $end
$var wire 1 Q sWhile8 $end
$var wire 1 R sWhile16 $end
$var wire 1 S sStart $end
$var wire 1 T sGarbage $end
$var wire 1 U sDone $end
$scope module fsDone $end
$var wire 1 ) clk $end
$var wire 1 F d $end
$var wire 1 V enable $end
$var wire 1 W reset $end
$var reg 1 U q $end
$upscope $end
$scope module fsGarbage $end
$var wire 1 ) clk $end
$var wire 1 G d $end
$var wire 1 X enable $end
$var wire 1 Y reset $end
$var reg 1 T q $end
$upscope $end
$scope module fsStart $end
$var wire 1 ) clk $end
$var wire 1 H d $end
$var wire 1 Z enable $end
$var wire 1 [ reset $end
$var reg 1 S q $end
$upscope $end
$scope module fsWhile16 $end
$var wire 1 ) clk $end
$var wire 1 I d $end
$var wire 1 \ enable $end
$var wire 1 ] reset $end
$var reg 1 R q $end
$upscope $end
$scope module fsWhile8 $end
$var wire 1 ) clk $end
$var wire 1 J d $end
$var wire 1 ^ enable $end
$var wire 1 _ reset $end
$var reg 1 Q q $end
$upscope $end
$scope module fsWrite16 $end
$var wire 1 ) clk $end
$var wire 1 K d $end
$var wire 1 ` enable $end
$var wire 1 a reset $end
$var reg 1 P q $end
$upscope $end
$scope module fsWrite8 $end
$var wire 1 ) clk $end
$var wire 1 L d $end
$var wire 1 b enable $end
$var wire 1 c reset $end
$var reg 1 O q $end
$upscope $end
$upscope $end
$upscope $end
$enddefinitions $end
$comment Show the parameter values. $end
$dumpall
b100000 =
$end
#0
$dumpvars
0c
1b
0a
1`
0_
1^
0]
1\
0[
1Z
0Y
1X
0W
1V
xU
xT
xS
xR
xQ
xP
xO
0N
xM
0L
0K
0J
0I
0H
1G
0F
b100000 E
bz D
bx C
bz B
bx A
bx @
b0xxxx ?
bx >
x<
b0 ;
bx :
bx 9
bx 8
bx 7
bx 6
b0xxxxxxxxxxxxxxxxxxxxxxxxxxxx 5
b0xxxxxxxxxxxxxxxxxxxxxxxxxxxxx 4
b0xxxx 3
b0xxx 2
b0xxxx 1
bx 0
bx /
bx .
1-
bx ,
0+
bx *
0)
x(
x'
x&
x%
x$
x#
x"
x!
$end
#1
b0 1
b0 ?
0%
0$
b0 4
b0 2
b0 5
b0 3
0!
b0 6
b0 @
b0 8
b0 7
0<
1#
b0 9
b0 :
1T
0&
0S
0Q
0R
0O
0P
0'
0U
1)
b0xxxx >
#2
b0 >
0)
b100000 .
0-
#3
1)
#4
1H
0G
0)
0"
0M
0(
b1111 *
b1111 /
b0 ,
b0 0
1N
1+
#5
1%
1$
0T
1&
1S
1)
#6
1J
0H
0)
0N
0+
#7
1F
0J
0%
0$
1Q
0&
0S
b1111 6
b1111 @
b1111 7
1)
#8
0)
#9
0Q
1'
1U
1)
#10
0)
#11
1)
#12
0)
#13
1)
#14
0)
#15
1)
#16
0)
#17
1)
#18
0)
#19
1)
#20
0)
#21
1)
#22
0)
#23
1)
#24
0)
#25
1)
#26
0)
b10111 .
#27
1)
#28
0)
b100000 .
#29
1)
#30
0F
1H
0)
1"
1M
1(
b10010001101000000 ,
b10010001101000000 0
1N
1+
#31
1%
1$
0'
0U
1&
1S
1)
#32
0H
b100000 E
1G
0)
1-
0N
0+
#33
0%
0$
b0 6
b0 @
b0 7
1T
0&
0S
1)
#34
0)
0-
